LICENSE
MANIFEST.in
README.md
requirements.txt
setup.py
robotframework_flaui_jim.egg-info/PKG-INFO
robotframework_flaui_jim.egg-info/SOURCES.txt
robotframework_flaui_jim.egg-info/dependency_links.txt
robotframework_flaui_jim.egg-info/requires.txt
robotframework_flaui_jim.egg-info/top_level.txt
src/FlaUILibrary/__init__.py
src/FlaUILibrary/pythonnetwrapper.py
src/FlaUILibrary/version.py
src/FlaUILibrary/bin/FlaUI.Core.dll
src/FlaUILibrary/bin/FlaUI.UIA2.dll
src/FlaUILibrary/bin/FlaUI.UIA3.dll
src/FlaUILibrary/bin/Interop.UIAutomationClient.dll
src/FlaUILibrary/flaui/__init__.py
src/FlaUILibrary/flaui/automation/__init__.py
src/FlaUILibrary/flaui/automation/uia.py
src/FlaUILibrary/flaui/automation/uia2.py
src/FlaUILibrary/flaui/automation/uia3.py
src/FlaUILibrary/flaui/enum/__init__.py
src/FlaUILibrary/flaui/enum/interfacetype.py
src/FlaUILibrary/flaui/enum/treeitemaction.py
src/FlaUILibrary/flaui/exception/__init__.py
src/FlaUILibrary/flaui/exception/flauierror.py
src/FlaUILibrary/flaui/interface/__init__.py
src/FlaUILibrary/flaui/interface/moduleinterface.py
src/FlaUILibrary/flaui/interface/valuecontainer.py
src/FlaUILibrary/flaui/interface/windowsautomationinterface.py
src/FlaUILibrary/flaui/module/__init__.py
src/FlaUILibrary/flaui/module/application.py
src/FlaUILibrary/flaui/module/checkbox.py
src/FlaUILibrary/flaui/module/combobox.py
src/FlaUILibrary/flaui/module/debug.py
src/FlaUILibrary/flaui/module/element.py
src/FlaUILibrary/flaui/module/grid.py
src/FlaUILibrary/flaui/module/keyboard.py
src/FlaUILibrary/flaui/module/mouse.py
src/FlaUILibrary/flaui/module/property.py
src/FlaUILibrary/flaui/module/screenshot.py
src/FlaUILibrary/flaui/module/selector.py
src/FlaUILibrary/flaui/module/tab.py
src/FlaUILibrary/flaui/module/textbox.py
src/FlaUILibrary/flaui/module/tooglebutton.py
src/FlaUILibrary/flaui/module/tree.py
src/FlaUILibrary/flaui/module/window.py
src/FlaUILibrary/flaui/util/__init__.py
src/FlaUILibrary/flaui/util/converter.py
src/FlaUILibrary/flaui/util/keyboardinputconverter.py
src/FlaUILibrary/flaui/util/treeitems.py
src/FlaUILibrary/flaui/util/treeitemsparser.py
src/FlaUILibrary/keywords/__init__.py
src/FlaUILibrary/keywords/application.py
src/FlaUILibrary/keywords/checkbox.py
