Metadata-Version: 2.1
Name: robotframework-flaui-jim
Version: 2.0.9
Summary: Windows GUI testing library for Robot Framework
Home-page: https://github.com/JimRevolutionist/robotframework-flaui-jim
Author: G DATA CyberDefense AG
Author-email: opensource@gdata.de
License: MIT
Platform: Windows
Classifier: Programming Language :: Python :: 3
Classifier: Programming Language :: Python :: 3.8
Classifier: Programming Language :: Python :: 3.9
Classifier: Programming Language :: Python :: 3.10
Classifier: License :: OSI Approved :: MIT License
Classifier: Operating System :: Microsoft
Classifier: Topic :: Software Development :: Testing
Classifier: Framework :: Robot Framework
Classifier: Framework :: Robot Framework :: Library
License-File: LICENSE
